[
    {
        "korean": "농작물",
        "vietnamese": "Rau màu, nông sản",
        "audio": "tu-vung-45-1.mp3"
    },
    {
        "korean": "재배",
        "vietnamese": "Công việc trồng trọt, canh tác",
        "audio": "tu-vung-45-2.mp3"
    },
    {
        "korean": "전작 (밭\/논에서 짓는 농사)",
        "vietnamese": "Làm đồng",
        "audio": "tu-vung-45-3.mp3"
    },
    {
        "korean": "논",
        "vietnamese": "Ruộng (trồng lúa)",
        "audio": "tu-vung-45-4.mp3"
    },
    {
        "korean": "비닐하우스",
        "vietnamese": "Nhà ni lông (nhà màng, nhà kính)",
        "audio": "tu-vung-45-5.mp3"
    },
    {
        "korean": "지주대",
        "vietnamese": "Cột, gậy chống",
        "audio": "tu-vung-45-6.mp3"
    },
    {
        "korean": "울타리망",
        "vietnamese": "Hàng rào",
        "audio": "tu-vung-45-7.mp3"
    },
    {
        "korean": "밭",
        "vietnamese": "Cánh đồng, ruộng nương, vườn",
        "audio": "tu-vung-45-8.mp3"
    },
    {
        "korean": "모판",
        "vietnamese": "Luống gieo giống",
        "audio": "tu-vung-45-9.mp3"
    },
    {
        "korean": "비료",
        "vietnamese": "Phân bón hóa học",
        "audio": "tu-vung-45-10.mp3"
    },
    {
        "korean": "삽",
        "vietnamese": "Xẻng",
        "audio": "tu-vung-45-11.mp3"
    },
    {
        "korean": "호미",
        "vietnamese": "Cuốc cầm tay, bay đào đất",
        "audio": "tu-vung-45-12.mp3"
    },
    {
        "korean": "곡괭이",
        "vietnamese": "Cuốc chim",
        "audio": "tu-vung-45-13.mp3"
    },
    {
        "korean": "경운기",
        "vietnamese": "Máy cày xới đất",
        "audio": "tu-vung-45-14.mp3"
    },
    {
        "korean": "울타리망을 설치하다",
        "vietnamese": "Lắp đặt hàng rào",
        "audio": "tu-vung-45-15.mp3"
    },
    {
        "korean": "울타리망을 치다",
        "vietnamese": "Dựng hàng rào",
        "audio": "tu-vung-45-16.mp3"
    },
    {
        "korean": "씨앗을 뿌리다",
        "vietnamese": "Gieo hạt",
        "audio": "tu-vung-45-17.mp3"
    },
    {
        "korean": "모종을 심다",
        "vietnamese": "Trồng cây non",
        "audio": "tu-vung-45-18.mp3"
    },
    {
        "korean": "모내기를 하다",
        "vietnamese": "Cấy lúa",
        "audio": "tu-vung-45-19.mp3"
    },
    {
        "korean": "거름을 주다",
        "vietnamese": "Bón phân chuồng",
        "audio": "tu-vung-45-20.mp3"
    },
    {
        "korean": "호스로 물을 대다",
        "vietnamese": "Cấp nước bằng đường ống",
        "audio": "tu-vung-45-21.mp3"
    },
    {
        "korean": "따다",
        "vietnamese": "Hái, vặt",
        "audio": "tu-vung-45-22.mp3"
    },
    {
        "korean": "뽑다",
        "vietnamese": "Nhổ",
        "audio": "tu-vung-45-23.mp3"
    },
    {
        "korean": "캐다",
        "vietnamese": "Bới, đào lên",
        "audio": "tu-vung-45-24.mp3"
    },
    {
        "korean": "파이다",
        "vietnamese": "Bị đào",
        "audio": "tu-vung-45-25.mp3"
    },
    {
        "korean": "따 먹다",
        "vietnamese": "Hái ăn, vặt ăn",
        "audio": "tu-vung-45-26.mp3"
    },
    {
        "korean": "벼를 베다",
        "vietnamese": "Gặt lúa",
        "audio": "tu-vung-45-27.mp3"
    },
    {
        "korean": "넘어지다",
        "vietnamese": "Ngã, đổ",
        "audio": "tu-vung-45-28.mp3"
    },
    {
        "korean": "고추",
        "vietnamese": "Ớt",
        "audio": "tu-vung-45-29.mp3"
    },
    {
        "korean": "오이",
        "vietnamese": "Dưa chuột",
        "audio": "tu-vung-45-30.mp3"
    },
    {
        "korean": "호박",
        "vietnamese": "Bí",
        "audio": "tu-vung-45-31.mp3"
    },
    {
        "korean": "배추",
        "vietnamese": "Cải thảo",
        "audio": "tu-vung-45-32.mp3"
    },
    {
        "korean": "무",
        "vietnamese": "Cải củ (củ cải trắng Hàn Quốc)",
        "audio": "tu-vung-45-33.mp3"
    },
    {
        "korean": "고구마",
        "vietnamese": "Khoai lang",
        "audio": "tu-vung-45-34.mp3"
    },
    {
        "korean": "감자",
        "vietnamese": "Khoai tây",
        "audio": "tu-vung-45-35.mp3"
    },
    {
        "korean": "낫",
        "vietnamese": "Cái liềm",
        "audio": "tu-vung-45-36.mp3"
    },
    {
        "korean": "고라니",
        "vietnamese": "Nai (loài nai nhỏ ở Hàn Quốc)",
        "audio": "tu-vung-45-37.mp3"
    },
    {
        "korean": "잎사귀",
        "vietnamese": "Lá cây non",
        "audio": "tu-vung-45-38.mp3"
    },
    {
        "korean": "나뭇가지",
        "vietnamese": "Nhành cây",
        "audio": "tu-vung-45-39.mp3"
    },
    {
        "korean": "트랙터",
        "vietnamese": "Máy kéo",
        "audio": "tu-vung-45-40.mp3"
    },
    {
        "korean": "케이블타이",
        "vietnamese": "Dây thít",
        "audio": "tu-vung-45-41.mp3"
    }
]